[
  {"id": 1, "name": "ئاسا جه‌نگی حسن محمد", "email": "asa.112824005@uor.edu.krd", "quiz": 0, "ass": 0, "sem": 2.5, "proj": 3.5, "theo": 5, "prac": 4, "rap": 3.5, "att": 2, "plus": 0, "total": 21},
  {"id": 2, "name": "ئاشتی احمد حمد امین", "email": "ashti.112824026@uor.edu.krd", "quiz": 0, "ass": 2.5, "sem": 5, "proj": 4.5, "theo": 6, "prac": 7, "rap": 2, "att": 2, "plus": 0, "total": 29},
  {"id": 3, "name": "ئامینە خدر احمد", "email": "amina.112824008@uor.edu.krd", "quiz": 2, "ass": 2, "sem": 2.5, "proj": 3.5, "theo": 4, "prac": 4, "rap": 3.5, "att": 2, "plus": 0, "total": 24},
  {"id": 4, "name": "باڤیل علی قادر نبی", "email": "bavel.112824015@uor.edu.krd", "quiz": 2, "ass": 2, "sem": 4, "proj": 4, "theo": 3, "prac": 4, "rap": 2, "att": 2, "plus": 0, "total": 23},
  {"id": 5, "name": "تروسکاي عبدالله‌ محمد", "email": "truskaiy.112824017@uor.edu.krd", "quiz": 2, "ass": 2, "sem": 5, "proj": 5, "theo": 6, "prac": 7, "rap": 2, "att": 2, "plus": 0, "total": 31},
  {"id": 6, "name": "چالیا احمدحسین رحیم", "email": "chalya.112824019@uor.edu.krd", "quiz": 2, "ass": 2.5, "sem": 2.5, "proj": 3.5, "theo": 5, "prac": 5, "rap": 3.5, "att": 2, "plus": 0, "total": 26},
  {"id": 7, "name": "حسن حمە عبدالله رسول", "email": "hassan.112824002@uor.edu.krd", "quiz": 2, "ass": 2.5, "sem": 5, "proj": 5, "theo": 8, "prac": 8, "rap": 3.5, "att": 2, "plus": 1, "total": 37},
  {"id": 8, "name": "خدیجە ابراهیم غفور", "email": "khadija.112824013@uor.edu.krd", "quiz": 2, "ass": 1.5, "sem": 5, "proj": 5, "theo": 7, "prac": 8, "rap": 4, "att": 2, "plus": 0.5, "total": 35},
  {"id": 9, "name": "دلشاد عولا رسول", "email": "dlshad.112824009@uor.edu.krd", "quiz": 0, "ass": 1.5, "sem": 3, "proj": 3.5, "theo": 3, "prac": 3, "rap": 2, "att": 2, "plus": 0, "total": 18},
  {"id": 10, "name": "دیاری باپیر عبداللە", "email": "dyari.112824010@uor.edu.krd", "quiz": 2, "ass": 1.5, "sem": 4.5, "proj": 4.5, "theo": 3, "prac": 7, "rap": 2, "att": 2, "plus": 0, "total": 27},
  {"id": 11, "name": "رەنجدەر على عبدالله", "email": "ranjdae.112824003@uor.edu.krd", "quiz": 2, "ass": 1.5, "sem": 5, "proj": 5, "theo": 5, "prac": 5, "rap": 3.5, "att": 2, "plus": 0, "total": 29},
  {"id": 12, "name": "ڕێزان عبداللە ابوبکر", "email": "rezan.112824029@uor.edu.krd", "quiz": 0, "ass": 3.5, "sem": 4.5, "proj": 4.5, "theo": 8, "prac": 8, "rap": 4, "att": 2, "plus": 0, "total": 35},
  {"id": 13, "name": "ژاڵە احمد رسول", "email": "zhala.112824031@uor.edu.krd", "quiz": 0, "ass": 1, "sem": 4.5, "proj": 4.5, "theo": 8, "prac": 5, "rap": 2, "att": 2, "plus": 0.5, "total": 28},
  {"id": 14, "name": "سارا علی حمه شیخ شیخه", "email": "sara.112824012@uor.edu.krd", "quiz": 2, "ass": 2, "sem": 4.5, "proj": 4.5, "theo": 6, "prac": 5, "rap": 4, "att": 2, "plus": 0, "total": 30},
  {"id": 15, "name": "ستار محمد قادر", "email": "star.112824001@uor.edu.krd", "quiz": 2, "ass": 2, "sem": 5, "proj": 5, "theo": 8, "prac": 9, "rap": 3.5, "att": 2, "plus": 0, "total": 37},
  {"id": 16, "name": "سەفین صالح محمد", "email": "safeen.112824023@uor.edu.krd", "quiz": 0, "ass": 0.5, "sem": 4, "proj": 4, "theo": 4, "prac": 6, "rap": 2, "att": 2, "plus": 0, "total": 23},
  {"id": 17, "name": "سەفەر محمد اسماعیل", "email": "safar.112824022@uor.edu.krd", "quiz": 0, "ass": 1.5, "sem": 3.5, "proj": 3.5, "theo": 5, "prac": 7, "rap": 4.5, "att": 2, "plus": 0, "total": 27},
  {"id": 18, "name": "شیروان وەهاب قادر", "email": "sherwan.112824020@uor.edu.krd", "quiz": 0, "ass": 0, "sem": 4, "proj": 4, "theo": 6, "prac": 6, "rap": 4, "att": 2, "plus": 0, "total": 26},
  {"id": 19, "name": "فه‌رهه‌نگ صلاح حمد قادر", "email": "unknown@uor.edu.krd", "quiz": 0, "ass": 0, "sem": 0, "proj": 0, "theo": 0, "prac": 0, "rap": 0, "att": 0, "plus": 0, "total": 0},
  {"id": 20, "name": "کارۆخ خدر حسن", "email": "karukh.112824028@uor.edu.krd", "quiz": 2, "ass": 3, "sem": 2.5, "proj": 3.5, "theo": 5, "prac": 7, "rap": 2.5, "att": 2, "plus": 0, "total": 28},
  {"id": 21, "name": "لاوین ابراهیم محمد", "email": "lawen.112824025@uor.edu.krd", "quiz": 0, "ass": 1, "sem": 3.5, "proj": 3.5, "theo": 4, "prac": 3, "rap": 3.5, "att": 2, "plus": 0, "total": 21},
  {"id": 22, "name": "محمد انوەر یحی", "email": "mahamad.112824032@uor.edu.krd", "quiz": 2, "ass": 2.5, "sem": 3.5, "proj": 4, "theo": 4, "prac": 8, "rap": 4.5, "att": 2, "plus": 0, "total": 31},
  {"id": 23, "name": "هۆشیار قادر ابراهیم", "email": "hushyar.112824021@uor.edu.krd", "quiz": 2, "ass": 3, "sem": 2.5, "proj": 3.5, "theo": 4, "prac": 7, "rap": 2.5, "att": 2, "plus": 1, "total": 28},
  {"id": 24, "name": "هۆشەنگ صالح محمد", "email": "hoshang.112824027@uor.edu.krd", "quiz": 0, "ass": 2, "sem": 3.5, "proj": 3.5, "theo": 3, "prac": 4, "rap": 4.5, "att": 2, "plus": 0, "total": 23},
  {"id": 25, "name": "هەژیر عمر احمد", "email": "hazhir.112824024@uor.edu.krd", "quiz": 0, "ass": 0, "sem": 4.5, "proj": 5, "theo": 5, "prac": 5, "rap": 2, "att": 2, "plus": 0, "total": 24}
]